{"gitee":[{"number":"I2D7YH","html_url":"https://gitee.com/ccknbc/blogroll/issues/I2D7YH","state":"open","title":"https://akilar.top/","body":{"name":"Akilarの糖果屋","link":"https://akilar.top/","avatar":"https://akilar.top/img/siteicon/favicon.png","descr":"期待您的光临！","--primary-color":"#49b1f5","border-width":"0px","border-style":"solid","--primary-rotate":"0deg","animation":"borderFlash 0s infinite alternate","img_animation":"auto_rotate_right 0s linear infinite","card_style":"card","screenshot":"https://cdn.jsdelivr.net/gh/ccknbc-actions/blogroll@webp/akilar.top.webp"},"label":[{"name":"小伙伴们","color":"#21BA45"}],"created_at":"2021-01-14T13:22:33+08:00","updated_at":"2021-04-03T18:11:07+08:00"},{"number":"I2DAH4","html_url":"https://gitee.com/ccknbc/blogroll/issues/I2DAH4","state":"open","title":"https://www.antmoe.com/","body":{"name":"小康博客","link":"https://www.antmoe.com/","avatar":"https://cdn.jsdelivr.net/gh/sviptzk/HexoStaticFile@latest/avatar.jpg","descr":"一个收藏回忆与分享技术的地方！","--primary-color":"#49b1f5","border-width":"0px","border-style":"solid","--primary-rotate":"0deg","animation":"borderFlash 0s infinite alternate","img_animation":"auto_rotate_right 0s linear infinite","card_style":"card","screenshot":"https://cdn.jsdelivr.net/gh/ccknbc-actions/blogroll@webp/www.antmoe.com.webp"},"label":[{"name":"小伙伴们","color":"#21BA45"}],"created_at":"2021-01-14T17:36:14+08:00","updated_at":"2021-04-03T18:13:06+08:00"},{"number":"I2DDRE","html_url":"https://gitee.com/ccknbc/blogroll/issues/I2DDRE","state":"open","title":"forever97.top","body":{"name":"未央の童话镇","link":"https://forever97.top","avatar":"https://forever97.top/img/avatar.png","descr":"在人海里梦游","--primary-color":"#49b1f5","border-width":"0px","border-style":"solid","--primary-rotate":"0deg","animation":"borderFlash 0s infinite alternate","img_animation":"auto_rotate_right 0s linear infinite","card_style":"card","screenshot":"https://cdn.jsdelivr.net/gh/ccknbc-actions/blogroll@webp/forever97.top.webp"},"label":[{"name":"小伙伴们","color":"#21BA45"}],"created_at":"2021-01-15T09:34:39+08:00","updated_at":"2021-03-12T17:20:00+08:00"},{"number":"I2DEDM","html_url":"https://gitee.com/ccknbc/blogroll/issues/I2DEDM","state":"open","title":"https://zykj.js.org","body":{"name":"卓越科技的Blog","link":"https://zykj.js.org","avatar":"https://cdn.jsdelivr.net/gh/zykjofficial/zykjofficial.github.io@master/img/avatar.png","descr":"Remarkable life,for science and technology.","--primary-color":"#49b1f5","border-width":"0px","border-style":"solid","--primary-rotate":"0deg","animation":"borderFlash 0s infinite alternate","img_animation":"auto_rotate_right 0s linear infinite","card_style":"card","screenshot":"https://cdn.jsdelivr.net/gh/ccknbc-actions/blogroll@webp/zykj.js.org.webp"},"label":[{"name":"小伙伴们","color":"#21BA45"}],"created_at":"2021-01-15T10:39:51+08:00","updated_at":"2021-04-03T18:13:02+08:00"},{"number":"I2DF4W","html_url":"https://gitee.com/ccknbc/blogroll/issues/I2DF4W","state":"open","title":"https://noionion.top/","body":{"name":"贰猹的小窝","link":"https://noionion.top/","avatar":"https://noionion-picture-bed.oss-cn-hangzhou.aliyuncs.com/img/head.jpg","descr":"用这生命中的每一秒，给自己一个不后悔的未来","--primary-color":"#49b1f5","border-width":"0px","border-style":"solid","--primary-rotate":"0deg","animation":"borderFlash 0s infinite alternate","img_animation":"auto_rotate_right 0s linear infinite","card_style":"card","screenshot":"https://cdn.jsdelivr.net/gh/ccknbc-actions/blogroll@webp/noionion.top.webp"},"label":[{"name":"小伙伴们","color":"#21BA45"}],"created_at":"2021-01-15T12:14:59+08:00","updated_at":"2021-03-12T17:23:08+08:00"},{"number":"I2DGBS","html_url":"https://gitee.com/ccknbc/blogroll/issues/I2DGBS","state":"open","title":"https://blog.imzjw.cn","body":{"name":"小嘉的部落格","link":"https://blog.imzjw.cn","avatar":"//cdn.jsdelivr.net/gh/zjwo/CDN/img/blog/avatar.jpg","descr":"好记性不如烂笔头","--primary-color":"#49b1f5","border-width":"0px","border-style":"solid","--primary-rotate":"0deg","animation":"borderFlash 0s infinite alternate","img_animation":"auto_rotate_right 0s linear infinite","card_style":"card","screenshot":"https://cdn.jsdelivr.net/gh/ccknbc-actions/blogroll@webp/blog.imzjw.cn.webp"},"label":[{"name":"小伙伴们","color":"#21BA45"}],"created_at":"2021-01-15T15:26:22+08:00","updated_at":"2021-04-03T18:11:35+08:00"},{"number":"I2DI8L","html_url":"https://gitee.com/ccknbc/blogroll/issues/I2DI8L","state":"open","title":"https://www.leader755.com/","body":{"name":"leader755 blogs","link":"https://www.leader755.com/","avatar":"https://cdn.leader755.com/public/wx_avatar.png","descr":"分享web前端相关的技术文章，会记录日常生活中的琐事和大家一起分享。","--primary-color":"#49b1f5","border-width":"0px","border-style":"solid","--primary-rotate":"0deg","animation":"borderFlash 0s infinite alternate","img_animation":"auto_rotate_right 0s linear infinite","card_style":"item","screenshot":""},"label":[{"name":"小伙伴们","color":"#21BA45"}],"created_at":"2021-01-15T20:40:09+08:00","updated_at":"2021-05-01T21:39:07+08:00"},{"number":"I2DKZG","html_url":"https://gitee.com/ccknbc/blogroll/issues/I2DKZG","state":"open","title":"https://www.heart-of-engine.top/","body":{"name":"Heart-of-engine","link":"https://www.heart-of-engine.top/","avatar":"https://heart-of-engine-picture-bed-1.oss-cn-beijing.aliyuncs.com/img/%E4%B8%AA%E4%BA%BA%E5%A4%B4%E5%83%8F.jpg","descr":"专注于数学与编程的完美结合,分享生活,分享知识","--primary-color":"#49b1f5","border-width":"0px","border-style":"solid","--primary-rotate":"0deg","animation":"borderFlash 0s infinite alternate","img_animation":"auto_rotate_right 0s linear infinite","card_style":"item","screenshot":""},"label":[{"name":"小伙伴们","color":"#21BA45"}],"created_at":"2021-01-16T23:26:52+08:00","updated_at":"2021-03-08T20:48:21+08:00"},{"number":"I2DTSZ","html_url":"https://gitee.com/ccknbc/blogroll/issues/I2DTSZ","state":"open","title":"https://blog.slqwq.cn","body":{"name":"SL's Blog","link":"https://blog.slqwq.cn","avatar":"https://rmt.dogedoge.com/fetch/hajeekn/storage/Logo@B_3508X4961.png","descr":"梦中做梦,做了个白日梦","--primary-color":"#49b1f5","border-width":"0px","border-style":"solid","--primary-rotate":"360deg","animation":"link_custom1 0s infinite alternate","img_animation":"auto_rotate_right 0s linear infinite","card_style":"card","screenshot":"https://cdn.jsdelivr.net/gh/ccknbc-actions/blogroll@webp/blog.slqwq.cn.webp"},"label":[{"name":"小伙伴们","color":"#21BA45"}],"created_at":"2021-01-19T11:21:44+08:00","updated_at":"2021-03-12T17:24:31+08:00"},{"number":"I2DZ0B","html_url":"https://gitee.com/ccknbc/blogroll/issues/I2DZ0B","state":"open","title":"https://blog.zhheo.com/","body":{"name":"Heo","link":"https://blog.zhheo.com/","avatar":"https://blog.zhheo.com/img/avatar.png","descr":"爱折腾的设计师","--primary-color":"#49b1f5","border-width":"0px","border-style":"solid","--primary-rotate":"0deg","animation":"borderFlash 0s infinite alternate","img_animation":"auto_rotate_right 0s linear infinite","card_style":"item","screenshot":""},"label":[{"name":"小伙伴们","color":"#21BA45"}],"created_at":"2021-01-19T17:39:38+08:00","updated_at":"2021-03-04T19:37:58+08:00"},{"number":"I2DZLR","html_url":"https://gitee.com/ccknbc/blogroll/issues/I2DZLR","state":"open","title":"https://blog.lete114.top","body":{"name":"Lete乐特","link":"https://blog.lete114.top","avatar":"https://www.lete114.top/img/avatar.png","descr":"人生只有一次，大胆的生活!!","--primary-color":"#49b1f5","border-width":"0px","border-style":"solid","--primary-rotate":"0deg","animation":"borderFlash 0s infinite alternate","img_animation":"auto_rotate_right 0s linear infinite","card_style":"card","screenshot":"https://cdn.jsdelivr.net/gh/ccknbc-actions/blogroll@webp/blog.lete114.top.webp"},"label":[{"name":"小伙伴们","color":"#21BA45"}],"created_at":"2021-01-19T19:28:30+08:00","updated_at":"2021-04-03T18:12:40+08:00"},{"number":"I2EAQF","html_url":"https://gitee.com/ccknbc/blogroll/issues/I2EAQF","state":"open","title":"https://ajie16.github.io/","body":{"name":"JeckXu","link":"https://ajie16.github.io/","avatar":"https://7.dusays.com/2021/01/20/a6d5355c85979.png","descr":"嵌入式技术记录与分享","--primary-color":"#49b1f5","border-width":"0px","border-style":"solid","--primary-rotate":"0deg","animation":"borderFlash 0s infinite alternate","img_animation":"auto_rotate_right 0s linear infinite","card_style":"item","screenshot":""},"label":[],"created_at":"2021-01-21T22:27:24+08:00","updated_at":"2021-03-13T14:23:55+08:00"},{"number":"I2MAOL","html_url":"https://gitee.com/ccknbc/blogroll/issues/I2MAOL","state":"open","title":"https://blog.keepdai.cn/","body":{"name":"呆逼の博客","link":"https://blog.keepdai.cn/","avatar":"https://cdn.jsdelivr.net/gh/Daibi-mua/jsdelivr@1.3/logo.png","descr":"一个初中生的博客","--primary-color":"#49b1f5","border-width":"0px","border-style":"solid","--primary-rotate":"0deg","animation":"borderFlash 0s infinite alternate","img_animation":"auto_rotate_right 0s linear infinite","card_style":"item","screenshot":""},"label":[{"name":"小伙伴们","color":"#21BA45"}],"created_at":"2021-01-25T21:23:59+08:00","updated_at":"2021-03-04T19:37:59+08:00"},{"number":"I2PLOK","html_url":"https://gitee.com/ccknbc/blogroll/issues/I2PLOK","state":"open","title":"https://cn.weikecc.top/","body":{"name":"WeiKe_Joe","link":"https://cn.weikecc.top/","avatar":"https://thirdqq.qlogo.cn/g?b=sdk&nk=3225454747&s=140","descr":"很帅很帅的中学生☺","--primary-color":"linear-gradient(to bottom, #232526, #414345)","border-width":"1px","border-style":"solid","--primary-rotate":"45deg","animation":"link_custom1 2s infinite alternate","img_animation":"auto_rotate_right 1s linear infinite","card_style":"item","screenshot":"https://cdn.jsdelivr.net/gh/ccknbc-actions/blogroll@webp/cn.weikecc.top.webp"},"label":[{"name":"小伙伴们","color":"#21BA45"}],"created_at":"2021-01-27T22:10:36+08:00","updated_at":"2021-03-08T20:11:20+08:00"},{"number":"I35AH9","html_url":"https://gitee.com/ccknbc/blogroll/issues/I35AH9","state":"open","title":"https://www.nesxc.com","body":{"name":"Nesxc","link":"https://www.nesxc.com","avatar":"https://cdn-1.nesxc.com/img/avatar.jpg","descr":"青石落晚巷 故人未还乡","--primary-color":"#49b1f5","border-width":"0px","border-style":"solid","--primary-rotate":"0deg","animation":"borderFlash 0s infinite alternate","img_animation":"auto_rotate_right 0s linear infinite","card_style":"card","screenshot":"https://cdn.jsdelivr.net/gh/ccknbc-actions/blogroll@webp/www.nesxc.com.webp"},"label":[{"name":"小伙伴们","color":"#21BA45"}],"created_at":"2021-02-03T11:13:20+08:00","updated_at":"2021-03-12T17:25:34+08:00"},{"number":"I37R2Q","html_url":"https://gitee.com/ccknbc/blogroll/issues/I37R2Q","state":"open","title":"https://zfe.space/","body":{"name":"小冰博客","link":"https://zfe.space/","avatar":"https://zfe.space/images/headimage.png","descr":"咕咕咕！","--primary-color":"#49b1f5","border-width":"0px","border-style":"solid","--primary-rotate":"0deg","animation":"borderFlash 0s infinite alternate","img_animation":"auto_rotate_right 0s linear infinite","card_style":"card","screenshot":"https://cdn.jsdelivr.net/gh/ccknbc-actions/blogroll@webp/zfe.space.webp"},"label":[{"name":"小伙伴们","color":"#21BA45"}],"created_at":"2021-02-08T16:11:27+08:00","updated_at":"2021-04-03T18:11:13+08:00"},{"number":"I37UJT","html_url":"https://gitee.com/ccknbc/blogroll/issues/I37UJT","state":"open","title":"https://blog.bugjava.cn/","body":{"name":"包子's Blog","link":"https://blog.bugjava.cn","avatar":"https://i.loli.net/2021/02/09/Q3zydh8JaruUcFN.png","descr":"一个练习Bug时长两年半的程序员建立的小站","--primary-color":"#49b1f5","border-width":"0px","border-style":"solid","--primary-rotate":"0deg","animation":"borderFlash 0s infinite alternate","img_animation":"auto_rotate_right 0s linear infinite","card_style":"item","screenshot":""},"label":[{"name":"小伙伴们","color":"#21BA45"}],"created_at":"2021-02-09T19:56:41+08:00","updated_at":"2021-03-04T19:38:00+08:00"},{"number":"I37XSL","html_url":"https://gitee.com/ccknbc/blogroll/issues/I37XSL","state":"open","title":"ql-isaac.cn","body":{"name":"学习与生活","link":"https://ql-isaac.cn/","avatar":"https://image.ql-isaac.cn/站长头像.jpg","descr":"It’s a beautiful day!","--primary-color":"#49b1f5","border-width":"0px","border-style":"solid","--primary-rotate":"0deg","animation":"borderFlash 0s infinite alternate","img_animation":"auto_rotate_right 0s linear infinite","card_style":"card","screenshot":"https://cdn.jsdelivr.net/gh/ccknbc-actions/blogroll@webp/ql-isaac.cn.webp"},"label":[{"name":"小伙伴们","color":"#21BA45"}],"created_at":"2021-02-13T18:56:24+08:00","updated_at":"2021-03-12T17:25:57+08:00"},{"number":"I39AYB","html_url":"https://gitee.com/ccknbc/blogroll/issues/I39AYB","state":"open","title":"https://wr0926.ml","body":{"name":"时过境迁Wayne博客","link":"https://wr0926.ml","avatar":"https://cdn.jsdelivr.net/gh/wayne0926/myphoto/img/avatar.jpg","descr":"以梦为马，不负韶华。","--primary-color":"#49b1f5","border-width":"0px","border-style":"solid","--primary-rotate":"0deg","animation":"borderFlash 0s infinite alternate","img_animation":"auto_rotate_right 0s linear infinite","card_style":"card","screenshot":"https://cdn.jsdelivr.net/gh/ccknbc-actions/blogroll@webp/wr0926.ml.webp"},"label":[{"name":"小伙伴们","color":"#21BA45"}],"created_at":"2021-02-27T20:52:34+08:00","updated_at":"2021-03-12T17:26:23+08:00"},{"number":"I39BNG","html_url":"https://gitee.com/ccknbc/blogroll/issues/I39BNG","state":"open","title":"https://cnhuazhu.gitee.io/","body":{"name":"花猪のBlog","link":"https://cnhuazhu.gitee.io/","avatar":"https://cdn.jsdelivr.net/gh/CNhuazhu/Image/avatar.jpg","descr":"佛系青年","--primary-color":"#49b1f5","border-width":"0px","border-style":"solid","--primary-rotate":"0deg","animation":"borderFlash 0s infinite alternate","img_animation":"auto_rotate_right 0s linear infinite","card_style":"item","screenshot":""},"label":[{"name":"小伙伴们","color":"#21BA45"}],"created_at":"2021-02-28T12:52:01+08:00","updated_at":"2021-03-04T19:38:01+08:00"},{"number":"I39NPS","html_url":"https://gitee.com/ccknbc/blogroll/issues/I39NPS","state":"open","title":"https://stevestudio.top","body":{"name":"Steve 祎","link":"https://stevestudio.top","avatar":"https://s3.ax1x.com/2021/02/03/yKETNn.jpg","descr":"Think Differently. 非同凡想。","--primary-color":"#49b1f5","border-width":"0px","border-style":"solid","--primary-rotate":"0deg","animation":"borderFlash 0s infinite alternate","img_animation":"auto_rotate_right 0s linear infinite","card_style":"item","screenshot":""},"label":[{"name":"小伙伴们","color":"#21BA45"}],"created_at":"2021-03-02T16:55:08+08:00","updated_at":"2021-04-19T09:34:33+08:00"},{"number":"I3AGXD","html_url":"https://gitee.com/ccknbc/blogroll/issues/I3AGXD","state":"open","title":"天昕","body":{"name":"天昕","link":"https://sutianxin.top","avatar":"https://gitee.com/sutianxin/my-hexo-blog-photo/raw/master/20210213111233.png","descr":"往者不谏 来者可追","--primary-color":"#49b1f5","border-width":"0px","border-style":"solid","--primary-rotate":"0deg","animation":"borderFlash 0s infinite alternate","img_animation":"auto_rotate_right 0s linear infinite","card_style":"item","screenshot":"https://gitee.com/sutianxin/my-hexo-blog-photo/raw/master/20210213113046.jpg"},"label":[{"name":"小伙伴们","color":"#21BA45"}],"created_at":"2021-03-08T15:13:51+08:00","updated_at":"2021-03-08T15:39:49+08:00"},{"number":"I3DVH6","html_url":"https://gitee.com/ccknbc/blogroll/issues/I3DVH6","state":"open","title":"https://blog.dhbxs.top","body":{"name":"灯火不休时","link":"https://blog.dhbxs.top","avatar":"https://cdn.jsdelivr.net/gh/zhao-v/blog-img/img/20201020000120.jpg ","descr":"所爱隔山海，山海皆可平；所念隔星河，星河不可及。","--primary-color":"","border-width":"","border-style":"","--primary-rotate":"","animation":"","img_animation":"","card_style":"","screenshot":""},"label":[{"name":"小伙伴们","color":"#21BA45"}],"created_at":"2021-03-27T22:10:05+08:00","updated_at":"2021-04-02T09:45:26+08:00"}],"github":[{"number":2,"html_url":"https://github.com/ccknbc-actions/blogroll/issues/2","state":"open","title":"https://blog.raxianch.moe","body":{"name":"快乐咸鱼の RaXianch 窝","link":"https://blog.raxianch.moe/","avatar":"https://q1.qlogo.cn/g?b=qq&nk=1025212779&s=5","descr":"为之则易，不为则难。","--primary-color":"#49b1f5","border-width":"0px","border-style":"solid","--primary-rotate":"0deg","animation":"borderFlash 0s infinite alternate","img_animation":"auto_rotate_right 0s linear infinite","card_style":"item","screenshot":""},"label":[{"name":"小伙伴们","color":"#30C014"}],"created_at":"2021-03-13T00:12:03Z","updated_at":"2021-03-19T02:08:16Z"},{"number":3,"html_url":"https://github.com/ccknbc-actions/blogroll/issues/3","state":"open","title":"https://blog.adil.com.cn","body":{"name":"Adil","link":"https://blog.adil.com.cn","avatar":"https://adil.com.cn/img/touxiang.jpg","descr":"生命不死，折腾不止","--primary-color":"#49b1f5","border-width":"0px","border-style":"solid","--primary-rotate":"0deg","animation":"borderFlash 0s infinite alternate","img_animation":"auto_rotate_right 0s linear infinite","card_style":"card","screenshot":""},"label":[{"name":"小伙伴们","color":"#30C014"}],"created_at":"2021-03-15T13:48:25Z","updated_at":"2021-03-16T07:09:07Z"},{"number":4,"html_url":"https://github.com/ccknbc-actions/blogroll/issues/4","state":"open","title":"https://ranas.cn/","body":{"name":"HopeLight|Blog","link":"https://ranas.cn/","avatar":"https://cdn.jsdelivr.net/gh/HopeLight/photo/blog/icon.png","descr":"生亦何欢，死亦何苦","--primary-color":"#49b1f5","border-width":"0px","border-style":"solid","--primary-rotate":"0deg","animation":"borderFlash 0s infinite alternate","img_animation":"auto_rotate_right 0s linear infinite","card_style":"item","screenshot":""},"label":[{"name":"小伙伴们","color":"#30C014"}],"created_at":"2021-04-01T17:43:49Z","updated_at":"2021-04-02T01:46:54Z"}],"date":"1619926600769"}